[{"StartDate":"\/Date(1735686000000)\/","EndDate":"\/Date(1767135600000)\/","Year":2025,"MandatoryDate":"\/Date(-62135596800000)\/","Id":445,"Name":"2025","Code":null,"Icon":null,"Sequence":0,"DisplayText":"2025"},{"StartDate":"\/Date(1704063600000)\/","EndDate":"\/Date(1735599600000)\/","Year":2024,"MandatoryDate":"\/Date(-62135596800000)\/","Id":431,"Name":"2024","Code":null,"Icon":null,"Sequence":0,"DisplayText":"2024"},{"StartDate":"\/Date(1672527600000)\/","EndDate":"\/Date(1703977200000)\/","Year":2023,"MandatoryDate":"\/Date(-62135596800000)\/","Id":420,"Name":"2023","Code":null,"Icon":null,"Sequence":0,"DisplayText":"2023"},{"StartDate":"\/Date(1640991600000)\/","EndDate":"\/Date(1672441200000)\/","Year":2022,"MandatoryDate":"\/Date(-62135596800000)\/","Id":160,"Name":"2022","Code":null,"Icon":null,"Sequence":0,"DisplayText":"2022"},{"StartDate":"\/Date(1609455600000)\/","EndDate":"\/Date(1640905200000)\/","Year":2021,"MandatoryDate":"\/Date(-62135596800000)\/","Id":149,"Name":"2021","Code":null,"Icon":null,"Sequence":0,"DisplayText":"2021"},{"StartDate":"\/Date(1577833200000)\/","EndDate":"\/Date(1609369200000)\/","Year":2020,"MandatoryDate":"\/Date(-62135596800000)\/","Id":129,"Name":"2020","Code":null,"Icon":null,"Sequence":0,"DisplayText":"2020"},{"StartDate":"\/Date(1546297200000)\/","EndDate":"\/Date(1577746800000)\/","Year":2019,"MandatoryDate":"\/Date(-62135596800000)\/","Id":128,"Name":"2019","Code":null,"Icon":null,"Sequence":0,"DisplayText":"2019"},{"StartDate":"\/Date(1514761200000)\/","EndDate":"\/Date(1546210800000)\/","Year":2018,"MandatoryDate":"\/Date(-62135596800000)\/","Id":123,"Name":"2018","Code":null,"Icon":null,"Sequence":0,"DisplayText":"2018"},{"StartDate":"\/Date(1483225200000)\/","EndDate":"\/Date(1514674800000)\/","Year":2017,"MandatoryDate":"\/Date(-62135596800000)\/","Id":22,"Name":"2017","Code":null,"Icon":null,"Sequence":0,"DisplayText":"2017"},{"StartDate":"\/Date(1451602800000)\/","EndDate":"\/Date(1483138800000)\/","Year":2016,"MandatoryDate":"\/Date(-62135596800000)\/","Id":12,"Name":"2016","Code":null,"Icon":null,"Sequence":0,"DisplayText":"2016"},{"StartDate":"\/Date(1420066800000)\/","EndDate":"\/Date(1451516400000)\/","Year":2015,"MandatoryDate":"\/Date(-62135596800000)\/","Id":4,"Name":"2015","Code":null,"Icon":null,"Sequence":0,"DisplayText":"2015"},{"StartDate":"\/Date(1388530800000)\/","EndDate":"\/Date(1419980400000)\/","Year":2014,"MandatoryDate":"\/Date(-62135596800000)\/","Id":102,"Name":"2014","Code":null,"Icon":null,"Sequence":0,"DisplayText":"2014"},{"StartDate":"\/Date(1356994800000)\/","EndDate":"\/Date(1388444400000)\/","Year":2013,"MandatoryDate":"\/Date(-62135596800000)\/","Id":103,"Name":"2013","Code":null,"Icon":null,"Sequence":0,"DisplayText":"2013"},{"StartDate":"\/Date(1325372400000)\/","EndDate":"\/Date(1356908400000)\/","Year":2012,"MandatoryDate":"\/Date(-62135596800000)\/","Id":104,"Name":"2012","Code":null,"Icon":null,"Sequence":0,"DisplayText":"2012"},{"StartDate":"\/Date(1293836400000)\/","EndDate":"\/Date(1325286000000)\/","Year":2011,"MandatoryDate":"\/Date(-62135596800000)\/","Id":105,"Name":"2011","Code":null,"Icon":null,"Sequence":0,"DisplayText":"2011"},{"StartDate":"\/Date(1262300400000)\/","EndDate":"\/Date(1293750000000)\/","Year":2010,"MandatoryDate":"\/Date(-62135596800000)\/","Id":106,"Name":"2010","Code":null,"Icon":null,"Sequence":0,"DisplayText":"2010"},{"StartDate":"\/Date(1230764400000)\/","EndDate":"\/Date(1262214000000)\/","Year":2009,"MandatoryDate":"\/Date(-62135596800000)\/","Id":107,"Name":"2009","Code":null,"Icon":null,"Sequence":0,"DisplayText":"2009"}]